{
  "daemon": "warwick_telescope",
  "log_name": "meaded@warwick",
  "control_machines": ["LocalHost"],
  "dome_daemon": "warwick_dome",
  "serial_port": "/dev/ttyS0",
  "serial_baud": 9600,
  "serial_timeout": 3,
  "latitude": 52.376861,
  "longitude": -1.583861,
  "altitude": 94,
  "initialize_timeout": 120,
  "slew_timeout": 90,
  "slew_loop_delay": 0.25,
  "idle_loop_delay": 1,
  "ha_soft_limits": [-82, 82],
  "dec_soft_limits": [-20, 85],
  "park_positions": {
    "zenith": {
      "desc": "pointing directly up",
      "alt": 90,
      "az": 0
    },
    "stow": {
      "desc": "positioned on the zero markers",
      "alt": 37.62,
      "az": 180
    }
  }
}
